{
  "schema": "vibeship_optimizer.snapshot.v1",
  "generated_at": "2026-02-15T13:22:34Z",
  "label": "before_chg-20260215-132034",
  "system": {
    "platform": "Windows-11-10.0.26100-SP0",
    "python": "3.13.5 (tags/v3.13.5:6cb20a2, Jun 11 2025, 16:15:46) [MSC v.1943 64 bit (AMD64)]",
    "executable": "C:\\Python313\\python.exe",
    "cwd": "C:\\Users\\USER\\Desktop\\vibeship-spark-intelligence\\tmp\\opt_base"
  },
  "git": {
    "is_git": true,
    "git_root": "C:\\Users\\USER\\Desktop\\vibeship-spark-intelligence\\tmp\\opt_base",
    "branch": "HEAD",
    "commit": "5fc9387763d6d3fe4a7975bad0222a3e6c0a1a74",
    "describe": "5fc9387",
    "dirty": true,
    "dirty_count": 1,
    "diff_stat": ""
  },
  "sizes": {
    "lib": {
      "path": "C:\\Users\\USER\\Desktop\\vibeship-spark-intelligence\\tmp\\opt_base\\lib",
      "bytes": 2653988
    },
    "scripts": {
      "path": "C:\\Users\\USER\\Desktop\\vibeship-spark-intelligence\\tmp\\opt_base\\scripts",
      "bytes": 473326
    },
    "docs": {
      "path": "C:\\Users\\USER\\Desktop\\vibeship-spark-intelligence\\tmp\\opt_base\\docs",
      "bytes": 1299401
    }
  },
  "timings": [
    {
      "name": "pipeline_health",
      "cmd": "python -m pytest -q tests/test_pipeline_health.py",
      "runs": 1,
      "timeout_s": 900,
      "last_rc": 0,
      "last_err": "",
      "mean_s": 1.9468,
      "p95_s": 1.9468,
      "all_s": [
        1.9468
      ]
    },
    {
      "name": "advisory_delta",
      "cmd": "python scripts/advisory_controlled_delta.py --rounds 40 --label optimizer --force-live",
      "runs": 1,
      "timeout_s": 1200,
      "last_rc": 0,
      "last_err": "",
      "mean_s": 29.1974,
      "p95_s": 29.1974,
      "all_s": [
        29.1974
      ]
    }
  ],
  "http": []
}